archtype_user_identification/__init__.py
archtype_user_identification/build_embedding.py
archtype_user_identification/classify_user.py
archtype_user_identification/token_extract.py
archtype_user_identification/twitter_preprocess.py
archtype_user_identification-0.0.1.dist-info/DESCRIPTION.rst
archtype_user_identification-0.0.1.dist-info/METADATA
archtype_user_identification-0.0.1.dist-info/RECORD
archtype_user_identification-0.0.1.dist-info/WHEEL
archtype_user_identification-0.0.1.dist-info/metadata.json
archtype_user_identification-0.0.1.dist-info/top_level.txt
